web_etl/__init__.py
web_etl/extract.py
web_etl/load.py
web_etl/transform.py
web_etl-0.1.1.dist-info/METADATA
web_etl-0.1.1.dist-info/WHEEL
web_etl-0.1.1.dist-info/top_level.txt
web_etl-0.1.1.dist-info/RECORD
