Metadata-Version: 2.4
Name: web_etl
Version: 0.1.1
Summary: An end-to-end ETL package for extracting HTML tables and transforming and loading data.
Author-email: Rose Wabere <rosewabere5@gmail.com>
License-Expression: MIT
Requires-Dist: pandas
Requires-Dist: requests
Requires-Dist: beautifulsoup4
Requires-Dist: sqlalchemy
